casaplotserver/__init__.py
casaplotserver/__main__.py
casaplotserver/__bin__/casaplotserver-x86_64.AppImage
casaplotserver/gotasks/__init__.py
casaplotserver/private/config.py
casaplotserver/private/ping_pb2.py
casaplotserver/private/ping_pb2_grpc.py
casaplotserver/private/plotserver_events_pb2.py
casaplotserver/private/plotserver_events_pb2_grpc.py
casaplotserver/private/plotserver_pb2.py
casaplotserver/private/plotserver_pb2_grpc.py
casaplotserver/private/shutdown_pb2.py
casaplotserver/private/shutdown_pb2_grpc.py
casaplotserver-2.0.3.dist-info/METADATA
casaplotserver-2.0.3.dist-info/WHEEL
casaplotserver-2.0.3.dist-info/top_level.txt
casaplotserver-2.0.3.dist-info/RECORD
